rolling_backup/__init__.py
rolling_backup/backup.py
rolling_backup-0.0.1.dist-info/LICENSE
rolling_backup-0.0.1.dist-info/METADATA
rolling_backup-0.0.1.dist-info/WHEEL
rolling_backup-0.0.1.dist-info/top_level.txt
rolling_backup-0.0.1.dist-info/RECORD
