Metadata-Version: 2.1
Name: rolling-backup
Version: 0.0.1
Summary: create rolling backups of a file
Home-page: https://github.com/RSabet/rolling-backup
Author: Ramin Sabet
Author-email: ramin.sabet@gmail.com
License: MIT
Project-URL: Bug Tracker, https://github.com/RSabet/rolling-backup/issues
Platform: UNKNOWN
Classifier: License :: OSI Approved :: MIT License
Classifier: Programming Language :: Python :: 3
Classifier: Operating System :: OS Independent
Requires-Python: >=3.6
License-File: LICENSE
